cctld_sdk/__init__.py
cctld_sdk/cctld.py
cctld_sdk/api/__init__.py
cctld_sdk/api/base_api.py
cctld_sdk/api/contact.py
cctld_sdk/api/decorator.py
cctld_sdk/api/domain.py
cctld_sdk/api/ns.py
cctld_sdk/api/registrar.py
cctld_sdk/common/__init__.py
cctld_sdk/common/exceptions.py
cctld_sdk/common/types.py
cctld_sdk/models/__init__.py
cctld_sdk/models/contact.py
cctld_sdk/models/domain.py
cctld_sdk-0.2.9.dist-info/METADATA
cctld_sdk-0.2.9.dist-info/WHEEL
cctld_sdk-0.2.9.dist-info/top_level.txt
cctld_sdk-0.2.9.dist-info/RECORD
