Metadata-Version: 2.1
Name: cctld-sdk
Version: 0.2.9
Summary: CCTLD SDK
Author: karimov.oqil@gmail.com, mr.arabboy@gmail.com
License: MIT
Requires-Dist: dicttoxml
Requires-Dist: requests
Requires-Dist: xmltodict
